src/__init__.py
src/core/__init__.py
src/core/arg_parser.py
src/core/log_config.py
src/exception/__init__.py
src/exception/file_exception.py
src/main.py
src/utils/__init__.py
src/utils/file_util.py
src/utils/gitlab_api_util.py
src/utils/ignore_keys.py
src/utils/yml_util.py
gitlab_ci_script_linter-0.1.3.dist-info/LICENCE
gitlab_ci_script_linter-0.1.3.dist-info/METADATA
gitlab_ci_script_linter-0.1.3.dist-info/WHEEL
gitlab_ci_script_linter-0.1.3.dist-info/entry_points.txt
gitlab_ci_script_linter-0.1.3.dist-info/RECORD
