Metadata-Version: 2.1
Name: gitlab-ci-script-linter
Version: 0.1.3
Summary: Collate expanded .gitlab-ci.yml script sections and lint scripts with Shellcheck
Home-page: https://gitlab.com/SydneyChadwick/gitlab-ci-linter
License: GPLv3
Author: Sydney Chadwick
Author-email: pseudossc@gmail.com
Requires-Python: >=3.12,<4.0
Classifier: License :: Other/Proprietary License
Classifier: Programming Language :: Python :: 3
Classifier: Programming Language :: Python :: 3.12
Requires-Dist: argparse (>=1.4.0,<2.0.0)
Requires-Dist: requests (>=2.32.3,<3.0.0)
Requires-Dist: ruamel-yaml (>=0.18.6,<0.19.0)
Project-URL: Repository, https://gitlab.com/SydneyChadwick/gitlab-ci-linter
